System Verilog/spi/spi.sv
// Esses parâmetros tornam o módulo flexível:
// DATA_BITS: Quantidade de bits transmitidos por transação (tamanho dos dados).
// CPOL (Clock Polarity): Polaridade do clock em repouso.
//     0 → SCK em nível baixo quando ocioso.
//     1 → SCK em nível alto quando ocioso.
// CPHA (Clock Phase): Fase de amostragem dos dados.
//     0 → MISO é lido na borda ativa (primeira transição).
//     1 → MISO é lido na borda inativa (segunda transição).
// BRDV: Divisor de clock → determina a frequência de SCK.
// LSBF: LSB First.
//     0 → MSB (bit mais significativo) primeiro.
//     1 → LSB (bit menos significativo) primeiro.

module spi #(parameter DATA_BITS=8, CPOL=0, CPHA=1, BRDV=2, LSBF=0)(
  input clk, n_rst, spi_enable, MISO,
  input [DATA_BITS-1:0] data_in,

  // ready_out: Indica que o SPI está pronto para uma nova transação
  // valid_out: Indica que data_out contém dados válidos.
  output SCK, SS, MOSI, ready_out, valid_out,
  output [DATA_BITS-1:0] data_out
);

  // Declaração dos estados simbólicos
  localparam [1:0]
  idle = 2'b00,
  data = 2'b01,
  trail = 2'b10;

  // idle: Espera por spi_enable.
  // data: Transmissão/recepção de bits.
  // trail: Encerramento da transação (delay final com SCK e SS).

  reg [1:0] state, next_state;
  reg [7:0] clk_cnt, next_clk; // 8 bits, considerando BRDV_max = 256
  reg [4:0] bit_cnt, next_bit; // 5 bits, considerando DATA_BITS_max = 32 bits
  reg SCK_reg, next_SCK;
  reg SS_reg, next_SS;
  reg [DATA_BITS-1:0] spi_data_reg, next_spi_data;
  reg MISO_reg;
  reg ready_reg, next_ready;
  reg valid_reg, next_valid;

  // Registradores da máquina de estados para o módulo SPI
  always_ff @(posedge clk, negedge n_rst) begin
      if (~n_rst) begin
          state <= idle;
          clk_cnt <= 0;
          bit_cnt <= 0;
          SCK_reg <= CPOL;
          SS_reg <= 1'b1;
          spi_data_reg <= '0;
          ready_reg <= 1'b0;
          valid_reg <= 1'b0;
      end
      else begin
          state <= next_state;
          clk_cnt <= next_clk;
          bit_cnt <= next_bit;
          SCK_reg <= next_SCK;
          spi_data_reg <= next_spi_data;
          SS_reg <= next_SS;
          ready_reg <= next_ready;
          valid_reg <= next_valid;
      end
  end

  // Lógica combinacional para a transição entre estados
  always_comb begin    
      next_state = state;
      next_clk = clk_cnt;
      next_bit = bit_cnt;
      case (state)
      idle: begin
          if (spi_enable) begin
              next_clk = 0;
              bit_cnt = 0;
              next_state = data;
          end
      end
      data: begin
          if (clk_cnt == BRDV-1) begin
              next_clk = 0;
              if (bit_cnt == DATA_BITS)
                next_state = trail;
              else
                next_bit = bit_cnt + 1;
          end
          else
            next_clk = clk_cnt + 1;
      end
      trail: begin
          if (clk_cnt == (BRDV/2)-1)
            next_state = idle;
          else
            next_clk = clk_cnt + 1;
      end
      endcase
  end

  // Lógica combinacional para o clock serial
  always_comb begin
      next_SCK = SCK_reg;
      case (state)
      idle: 
        next_SCK = CPOL;
      data: begin
          if (clk_cnt == (BRDV/2)-1 || clk_cnt == BRDV-1)
            next_SCK = ~SCK_reg;
      end
      trail: 
        next_SCK = SCK_reg;
      endcase
  end

  // Lógica combinacional para os registradores de dados 
  // e para os sinais ready_out, valid_out e SS
  always @* begin
      next_SS = SS_reg;
      next_spi_data = spi_data_reg;
      next_ready = ready_reg;
      next_valid = valid_reg;
      case (state)
      idle: begin
          next_ready = 1'b1;
          next_valid = 1'b0;
          if (spi_enable) begin
              next_SS = 1'b0;
              next_spi_data = data_in;
          end
      end
      data: begin
          next_ready = 1'b0;

          // Amostragem do MISO na primeira borda (para CPHA = 0)
          if (clk_cnt == 0 && CPHA == 0) begin
              MISO_reg = MISO;
          end

          // Amostragem de MISO em CPHA = 1, após a primeira transição
          if (clk_cnt == (BRDV/2)-1) begin
              if (CPHA == 0) begin
                  // segunda amostragem (para os demais bits)
                  MISO_reg = MISO;
              end else if (CPHA == 1 && bit_cnt > 0) begin
                  if (LSBF == 0)
                      next_spi_data = {spi_data_reg[DATA_BITS-2:0], MISO_reg};
                  else
                      next_spi_data = {MISO_reg, spi_data_reg[DATA_BITS-1:1]};
              end
          end

          // Envio de MISO_reg para data_out no final do ciclo
          if (clk_cnt == BRDV-1) begin
              if (CPHA == 0) begin
                  next_valid = 1'b1;
                  if (LSBF == 0)
                      next_spi_data = {spi_data_reg[DATA_BITS-2:0], MISO_reg};
                  else
                      next_spi_data = {MISO_reg, spi_data_reg[DATA_BITS-1:1]};
              end else begin
                  MISO_reg = MISO;
              end
          end
      end
      trail: begin
          if (clk_cnt == (BRDV/2)-1) begin
              next_SS = 1'b1;
              if (CPHA == 1) begin
                  next_valid = 1'b1;
                  if (LSBF == 0)
                  next_spi_data = {spi_data_reg[DATA_BITS-2:0], MISO_reg};
                  else
                  next_spi_data = {MISO_reg, spi_data_reg[DATA_BITS-1:1]};
              end
          end
      end
      endcase
  end

  // Direcionamento dos registrasdores para as saídas
  assign SCK = SCK_reg;
  assign data_out = spi_data_reg;
  assign SS = SS_reg;
  assign MOSI = LSBF == 0 ? spi_data_reg[DATA_BITS-1] : spi_data_reg[0];
  assign ready_out = ready_reg;
  assign valid_out = valid_reg;

endmodule

System/spi/tb_spi.sv
`timescale 1ns / 1ps

module tb_spi;

  // Parâmetros de configuração
  localparam DATA_BITS = 8;
  localparam CPOL = 0;
  localparam CPHA = 1;
  localparam BRDV = 4;
  localparam LSBF = 0;

  // Sinais
  logic clk, n_rst;
  logic spi_enable;
  logic MISO;
  logic [DATA_BITS-1:0] data_in;
  logic SCK, SS, MOSI, ready_out, valid_out;
  logic [DATA_BITS-1:0] data_out;
  logic [DATA_BITS-1:0] miso_data;

  // Instancia o módulo SPI
  spi #(
    .DATA_BITS(DATA_BITS),
    .CPOL(CPOL),
    .CPHA(CPHA),
    .BRDV(BRDV),
    .LSBF(LSBF)
  ) dut (
    .clk(clk),
    .n_rst(n_rst),
    .spi_enable(spi_enable),
    .MISO(MISO),
    .data_in(data_in),
    .SCK(SCK),
    .SS(SS),
    .MOSI(MOSI),
    .ready_out(ready_out),
    .valid_out(valid_out),
    .data_out(data_out)
  );

  // Clock de 100 MHz (período = 10ns)
  always #5 clk = ~clk;

  initial begin
    $dumpfile("waveform.vcd");
    $dumpvars(0, tb_spi);

    // Inicializa sinais
    clk = 0;
    n_rst = 0;
    spi_enable = 0;
    
    // Dado a ser transmitido pelo mestre (MOSI)
    data_in = 8'b10101010; 
    MISO = 0;

    // Reset
    #20;
    n_rst = 1;

    // Aguarda o SPI estar pronto
    @(posedge ready_out);

    // Inicia a transação
    spi_enable = 1;
    @(posedge clk);
    spi_enable = 0;

    // Aguarda início da transação SPI
    wait (SS == 0);

    // Dado que será recebido do escravo pelo MISO
    miso_data = 8'b11001100;

    // Envia bit a bit do MISO sincronizado com SCK
    for (int i = 0; i < DATA_BITS; i++) begin
      // Borda de descida do clock SPI
      @(negedge SCK);
      if (LSBF)
        MISO = miso_data[i];
      else
        MISO = miso_data[DATA_BITS - 1 - i];
    end

    // Aguarda finalização e dados válidos
    wait (valid_out);

    // Mostra o resultado
    $display("Recebido via SPI: %b", data_out);
    if (data_out === miso_data)
      $display("SUCESSO: Dados recebidos corretamente!");
    else
      $display("ERRO: Dados incorretos!");

    #5000;
    $finish;
  end

endmodule

System/spi/waveform.vcd
$date
	Tue Jun 24 10:19:22 2025
$end
$version
	Icarus Verilog
$end
$timescale
	1ps
$end
$scope module tb_spi $end
$var wire 1 ! valid_out $end
$var wire 1 " ready_out $end
$var wire 8 # data_out [7:0] $end
$var wire 1 $ SS $end
$var wire 1 % SCK $end
$var wire 1 & MOSI $end
$var reg 1 ' MISO $end
$var reg 1 ( clk $end
$var reg 8 ) data_in [7:0] $end
$var reg 8 * miso_data [7:0] $end
$var reg 1 + n_rst $end
$var reg 1 , spi_enable $end
$scope module dut $end
$var wire 1 ' MISO $end
$var wire 1 % SCK $end
$var wire 1 $ SS $end
$var wire 1 ( clk $end
$var wire 8 - data_in [7:0] $end
$var wire 8 . data_out [7:0] $end
$var wire 1 + n_rst $end
$var wire 1 " ready_out $end
$var wire 1 , spi_enable $end
$var wire 1 ! valid_out $end
$var wire 1 & MOSI $end
$var reg 1 / MISO_reg $end
$var reg 1 0 SCK_reg $end
$var reg 1 1 SS_reg $end
$var reg 5 2 bit_cnt [4:0] $end
$var reg 8 3 clk_cnt [7:0] $end
$var reg 1 4 next_SCK $end
$var reg 1 5 next_SS $end
$var reg 5 6 next_bit [4:0] $end
$var reg 8 7 next_clk [7:0] $end
$var reg 1 8 next_ready $end
$var reg 8 9 next_spi_data [7:0] $end
$var reg 2 : next_state [1:0] $end
$var reg 1 ; next_valid $end
$var reg 1 < ready_reg $end
$var reg 8 = spi_data_reg [7:0] $end
$var reg 2 > state [1:0] $end
$var reg 1 ? valid_reg $end
$upscope $end
$scope begin $ivl_for_loop0 $end
$var integer 32 @ i [31:0] $end
$upscope $end
$upscope $end
$enddefinitions $end
#0
$dumpvars
b0 @
0?
b0 >
b0 =
0<
0;
b0 :
b0 9
18
b0 7
b0 6
15
04
b0 3
b0 2
11
00
x/
b0 .
b10101010 -
0,
0+
bx *
b10101010 )
0(
0'
0&
0%
1$
b0 #
0"
0!
$end
#5000
1(
#10000
0(
#15000
1(
#20000
0(
1+
#25000
b1 :
b10101010 9
05
1,
1"
1<
1(
#30000
0(
#35000
b11001100 *
1&
08
b1 7
0$
01
b10101010 #
b10101010 .
b10101010 =
b1 >
b10101010 9
05
b1 :
0,
1(
#40000
0(
#45000
14
b10 7
0"
0<
b1 3
1(
#50000
0(
#55000
b11 7
1%
10
b10 3
1(
#60000
0(
#65000
0/
04
b1 6
b0 7
b11 3
1(
#70000
0(
#75000
b1 @
1'
b1 7
0%
00
b1 2
b0 3
1(
#80000
0(
#85000
b1010100 9
14
b10 7
b1 3
1(
#90000
0(
#95000
0&
b11 7
b1010100 #
b1010100 .
b1010100 =
1%
10
b10 3
1(
#100000
0(
#105000
1/
04
b10 6
b0 7
b11 3
1(
#110000
0(
#115000
b10 @
b1 7
0%
00
b10 2
b0 3
1(
#120000
0(
#125000
b10101001 9
14
b10 7
b1 3
1(
#130000
0(
#135000
1&
b11 7
b10101001 #
b10101001 .
b10101001 =
1%
10
b10 3
1(
#140000
0(
#145000
04
b11 6
b0 7
b11 3
1(
#150000
0(
#155000
b11 @
0'
b1 7
0%
00
b11 2
b0 3
1(
#160000
0(
#165000
b1010011 9
14
b10 7
b1 3
1(
#170000
0(
#175000
0&
b11 7
b1010011 #
b1010011 .
b1010011 =
1%
10
b10 3
1(
#180000
0(
#185000
0/
04
b100 6
b0 7
b11 3
1(
#190000
0(
#195000
b100 @
b1 7
0%
00
b100 2
b0 3
1(
#200000
0(
#205000
b10100110 9
14
b10 7
b1 3
1(
#210000
0(
#215000
1&
b11 7
b10100110 #
b10100110 .
b10100110 =
1%
10
b10 3
1(
#220000
0(
#225000
04
b101 6
b0 7
b11 3
1(
#230000
0(
#235000
b101 @
1'
b1 7
0%
00
b101 2
b0 3
1(
#240000
0(
#245000
b1001100 9
14
b10 7
b1 3
1(
#250000
0(
#255000
0&
b11 7
b1001100 #
b1001100 .
b1001100 =
1%
10
b10 3
1(
#260000
0(
#265000
1/
04
b110 6
b0 7
b11 3
1(
#270000
0(
#275000
b110 @
b1 7
0%
00
b110 2
b0 3
1(
#280000
0(
#285000
b10011001 9
14
b10 7
b1 3
1(
#290000
0(
#295000
1&
b11 7
b10011001 #
b10011001 .
b10011001 =
1%
10
b10 3
1(
#300000
0(
#305000
04
b111 6
b0 7
b11 3
1(
#310000
0(
#315000
b111 @
0'
b1 7
0%
00
b111 2
b0 3
1(
#320000
0(
#325000
b110011 9
14
b10 7
b1 3
1(
#330000
0(
#335000
0&
b11 7
b110011 #
b110011 .
b110011 =
1%
10
b10 3
1(
#340000
0(
#345000
0/
04
b1000 6
b0 7
b11 3
1(
#350000
0(
#355000
b1000 @
b1 7
0%
00
b1000 2
b0 3
1(
#360000
0(
#365000
b1100110 9
14
b10 7
b1 3
1(
#370000
0(
#375000
b11 7
b1100110 #
b1100110 .
b1100110 =
1%
10
b10 3
1(
#380000
0(
#385000
04
b10 :
b0 7
b11 3
1(
#390000
0(
#395000
b1 7
0%
00
b0 3
b10 >
1(
#400000
0(
#405000
b11001100 9
1;
15
b0 :
b1 3
1(
#410000
0(
#415000
1&
0;
18
1!
1?
1$
11
b11001100 #
b11001100 .
b11001100 =
b0 >
1(
#420000
0(
#425000
0!
0?
1"
1<
1(
